logging_library2/__init__.py
logging_library2/logger.py
logging_library-0.3.0.dist-info/METADATA
logging_library-0.3.0.dist-info/WHEEL
logging_library-0.3.0.dist-info/top_level.txt
logging_library-0.3.0.dist-info/RECORD
