Metadata-Version: 2.1
Name: logging-library
Version: 0.3.0
Summary: A custom logging library
Home-page: https://gitlab.com/adv_python_maglnuse/assignment3
Author: maglnuse
Author-email: n_maulen@kbtu.kz
License: MIT
Classifier: License :: OSI Approved :: MIT License
Classifier: Programming Language :: Python :: 3
Classifier: Programming Language :: Python :: 3.6
Classifier: Programming Language :: Python :: 3.7
Classifier: Programming Language :: Python :: 3.8
Classifier: Programming Language :: Python :: 3.9
